polylabel_pyo3-0.1.1.dist-info/METADATA
polylabel_pyo3-0.1.1.dist-info/WHEEL
polylabel_pyo3/__init__.pyi
polylabel_pyo3/__init__.py
polylabel_pyo3/py.typed
polylabel_pyo3/polylabel_pyo3.cpython-38-darwin.so
polylabel_pyo3-0.1.1.dist-info/RECORD
