Metadata-Version: 2.1
Name: polylabel-pyo3
Version: 0.1.1
Classifier: Programming Language :: Rust
Classifier: Programming Language :: Python
Classifier: Programming Language :: Python :: 3
Classifier: Programming Language :: Python :: Implementation :: CPython
Summary: Polylabel algorithm for optimal label centers in polygons (python wheels).
Keywords: geometry,geo,polylabel,opimization,python,pyo3
Home-Page: https://github.com/MoonVision/polylabel-pyo3
Author: Alexander Hirner <alexander.hirner@moonvision.io>
Author-email: Alexander Hirner <alexander.hirner@moonvision.io>
License: MIT
Requires-Python: >=3.6
Project-URL: Source Code, https://github.com/MoonVision/polylabel-pyo3
